{
	"info": {
		"_postman_id": "dfe36770-4827-49ae-98e9-5f4e589fa4d4",
		"name": "NodeJS training program",
		"schema": "https://schema.getpostman.com/json/collection/v2.1.0/collection.json"
	},
	"item": [
		{
			"name": "Get names",
			"request": {
				"method": "GET",
				"header": [],
				"url": {
					"raw": "http://localhost:3000",
					"protocol": "http",
					"host": [
						"localhost"
					],
					"port": "3000"
				}
			},
			"response": []
		},
		{
			"name": "Get names with search",
			"request": {
				"method": "GET",
				"header": [],
				"url": {
					"raw": "http://localhost:3000",
					"protocol": "http",
					"host": [
						"localhost"
					],
					"port": "3000"
				}
			},
			"response": []
		},
		{
			"name": "Add name",
			"request": {
				"method": "POST",
				"header": [],
				"body": {
					"mode": "raw",
					"raw": "{\n    \"name\": \"Rafael\"\n}",
					"options": {
						"raw": {
							"language": "json"
						}
					}
				},
				"url": {
					"raw": "http://localhost:3000",
					"protocol": "http",
					"host": [
						"localhost"
					],
					"port": "3000"
				}
			},
			"response": []
		}
	]
}